rdpurchasestorage/EcsInterface.py
rdpurchasestorage/__init__.py
rdpurchasestorage/mainModel.py
rdpurchasestorage/metadata.py
rdpurchasestorage/operation.py
rdpurchasestorage/utility.py
rdpurchasestorage-1.2.2.dist-info/METADATA
rdpurchasestorage-1.2.2.dist-info/WHEEL
rdpurchasestorage-1.2.2.dist-info/top_level.txt
rdpurchasestorage-1.2.2.dist-info/RECORD
